{
    "class": "DepictionTabView",
    "headerImage": "https://invalidunit.github.io/repo/Depictions/Default/top_1.png",
    "tintColor": "#FF4455",
    "minVersion": "0.3",
    "tabs": [
        {
            "class": "DepictionStackView",
            "tabname": "描述",
            "views": [
                {
                    "class": "DepictionSubheaderView",
                    "title": "将 iOS14 横屏时的亮度和声音占用三格改回两格",
                    "useBoldText": true,
                    "useBottomMargin": false
                },
                {
                    "class": "DepictionScreenshotsView",
                    "itemCornerRadius": 6,
                    "itemSize": "{160, 346.4533333333333}",
                    "screenshots": [
                        {
                            "accessibilityText": "Screenshot",
                            "url": "https://invalidunit.github.io/repo/Depictions/Default/Screenshot_01.png"
                        },
                        {
                            "accessibilityText": "Screenshot",
                            "url": "https://invalidunit.github.io/repo/Depictions/Default/Screenshot_02.png"
                        }
                    ]
                },
                {
                    "class": "DepictionSpacerView",
                    "spacing": 16
                },
                {
                    "class": "DepictionSeparatorView"
                },
                {
                    "class": "DepictionSpacerView",
                    "spacing": 16
                },
                {
                    "class": "DepictionHeaderView",
                    "title": "详情",
                    "useBoldText": true,
                    "useBottomMargin": false
                },
                {
                    "class": "DepictionSpacerView",
                    "spacing": 8
                },
                {
                    "class": "DepictionTableTextView",
                    "text": "zhaonan",
                    "title": "作者"
                },
                {
                    "class": "DepictionTableTextView",
                    "text": "0.1.1",
                    "title": "最新版本"
                },
                {
                    "class": "DepictionTableTextView",
                    "text": "14.0 - 14.9",
                    "title": "支持系统范围"
                },
                {
                    "class": "DepictionTableTextView",
                    "text": "2020 年 11 月 09 日",
                    "title": "最后更新日期"
                },
                {
                    "class": "DepictionSpacerView",
                    "spacing": 16
                },
            ]
        },
        {
            "class": "DepictionStackView",
            "tabname": "更新日志",
            "views": [
                {
                    "class": "DepictionSubheaderView",
                    "title": "0.1.1",
                    "useBoldText": true,
                    "useBottomMargin": false
                },
                {
                    "class": "DepictionMarkdownView",
                    "markdown": "修复错误",
                    "useRawFormat": true
                },
                {
                    "class": "DepictionSubheaderView",
                    "title": "0.1.0",
                    "useBoldText": true,
                    "useBottomMargin": false
                },
                {
                    "class": "DepictionMarkdownView",
                    "markdown": "初始版本",
                    "useRawFormat": true
                }
            ]
        }
    ],
}