{
    "class": "DepictionTabView",
    "headerImage": "https://invalidunit.github.io/repo/Depictions/com.nan.openccmm/top.png",
    "tintColor": "#FF4455",
    "minVersion": "0.3",
    "tabs": [
        {
            "class": "DepictionStackView",
            "tabname": "描述",
            "views": [
                {
                    "class": "DepictionSubheaderView",
                    "title": "激活原生 iPhone 控制中心静音模块",
                    "useBoldText": true,
                    "useBottomMargin": false
                },
                {
                    "class": "DepictionScreenshotsView",
                    "itemCornerRadius": 6,
                    "itemSize": "{160, 346.4533333333333}",
                    "screenshots": [
                        {
                            "accessibilityText": "Screenshot",
                            "url": "https://Invalidunit.github.io/repo/Depictions/com.nan.openccmm/Screenshot_01.png"
                        },
                        {
                            "accessibilityText": "Screenshot",
                            "url": "https://Invalidunit.github.io/repo/Depictions/com.nan.openccmm/Screenshot_02.png"
                        }
                    ]
                },
                {
                    "class": "DepictionSubheaderView",
                    "title": "为 iPhone 启用 CC 模块 '静音模式'",
                    "useBoldText": true,
                    "useBottomMargin": false
                },
                {
                    "class": "DepictionSubheaderView",
                    "title": "因为是修改系统文件，所以重启后静音按钮还在。",
                    "useBoldText": true,
                    "useBottomMargin": false
                },
                {
                    "class": "DepictionSpacerView",
                    "spacing": 16
                },
                {
                    "class": "DepictionSeparatorView"
                },
                {
                    "class": "DepictionSpacerView",
                    "spacing": 16
                },
                {
                    "class": "DepictionHeaderView",
                    "title": "详情",
                    "useBoldText": true,
                    "useBottomMargin": false
                },
                {
                    "class": "DepictionSpacerView",
                    "spacing": 8
                },
                {
                    "class": "DepictionTableTextView",
                    "text": "zhaonan",
                    "title": "作者"
                },
                {
                    "class": "DepictionTableTextView",
                    "text": "0.1.3",
                    "title": "最新版本"
                },
                {
                    "class": "DepictionTableTextView",
                    "text": "11.0 - 14.9",
                    "title": "支持系统范围"
                },
                {
                    "class": "DepictionTableTextView",
                    "text": "2020 年 11 月 09 日",
                    "title": "最后更新日期"
                },
                {
                    "class": "DepictionSpacerView",
                    "spacing": 16
                }
            ]
        },
        {
            "class": "DepictionStackView",
            "tabname": "更新日志",
            "views": [
                {
                    "class": "DepictionSubheaderView",
                    "title": "0.1.3",
                    "useBoldText": true,
                    "useBottomMargin": false
                },
                {
                    "class": "DepictionMarkdownView",
                    "markdown": "用了更好的还原方式",
                    "useRawFormat": true
                },
                {
                    "class": "DepictionSubheaderView",
                    "title": "0.1.2",
                    "useBoldText": true,
                    "useBottomMargin": false
                },
                {
                    "class": "DepictionMarkdownView",
                    "markdown": "更新支持 iOS13",
                    "useRawFormat": true
                },
                {
                    "class": "DepictionSubheaderView",
                    "title": "0.1.1",
                    "useBoldText": true,
                    "useBottomMargin": false
                },
                {
                    "class": "DepictionMarkdownView",
                    "markdown": "删除本地图标",
                    "useRawFormat": true
                },
                {
                    "class": "DepictionSubheaderView",
                    "title": "0.1.0",
                    "useBoldText": true,
                    "useBottomMargin": false
                },
                {
                    "class": "DepictionMarkdownView",
                    "markdown": "初始版本",
                    "useRawFormat": true
                }
            ]
        }
    ],
}